setup.py
django_serialize_model_graph/__init__.py
django_serialize_model_graph/decode.py
django_serialize_model_graph/encode.py
django_serialize_model_graph/entities.py
django_serialize_model_graph/models.py
django_serialize_model_graph/tests.py
django_serialize_model_graph/views.py
django_serialize_model_graph.egg-info/PKG-INFO
django_serialize_model_graph.egg-info/SOURCES.txt
django_serialize_model_graph.egg-info/dependency_links.txt
django_serialize_model_graph.egg-info/top_level.txt