Metadata-Version: 1.0
Name: django-serialize-model-graph
Version: 1.2.0
Summary: Django Serialize Model Graph -- utility for serializing graph of models for django.
Home-page: https://bitbucket.org/k_bx/django_serialize_model_graph/
Author: Konstantine Rybnikov
Author-email: k-bx@k-bx.com
License: BSD
Platform: UNKNOWN
